{"version":1,"resource":"file:///opt/lampp/htdocs/es14/unlogin.php","entries":[{"id":"7tgy.php","timestamp":1700304435681},{"id":"KGvT.php","timestamp":1700304454845},{"id":"FMFX.php","timestamp":1700304466718},{"id":"EDsN.php","timestamp":1700304621737},{"id":"qUs3.php","timestamp":1700304670572},{"id":"W78g.php","timestamp":1700304705795},{"id":"YYek.php","timestamp":1700304741538},{"id":"tfhK.php","timestamp":1700304755037},{"id":"LOeV.php","timestamp":1700304799793},{"id":"s53b.php","timestamp":1700304888928},{"id":"y2eM.php","timestamp":1700304908765},{"id":"nuK8.php","timestamp":1700304938284},{"id":"rLNM.php","timestamp":1700304958757},{"id":"EPoX.php","timestamp":1700304992263},{"id":"7lgP.php","timestamp":1700305079275},{"id":"rKzU.php","timestamp":1700305108818},{"id":"9uB9.php","timestamp":1700305129641},{"id":"atQl.php","timestamp":1700305149028},{"id":"6gvX.php","timestamp":1700305174057},{"id":"YHG2.php","timestamp":1700305204437},{"id":"ooRv.php","timestamp":1700305245617},{"id":"dvaH.php","timestamp":1700305608583},{"id":"QWy3.php","timestamp":1700387561268},{"id":"lC01.php","timestamp":1700387580350}]}