{"version":1,"resource":"file:///home/inkeaton/.config/nixos/modules/system/software/user.nix","entries":[{"id":"ZVNB.nix","timestamp":1706808974361},{"id":"nrp3.nix","timestamp":1706808988321},{"id":"4xnv.nix","timestamp":1706809020253},{"id":"hp8h.nix","timestamp":1706809046088},{"id":"AwH3.nix","timestamp":1706809057214},{"id":"DOAZ.nix","source":"undoRedo.source","timestamp":1706809061663},{"id":"kzbI.nix","timestamp":1706809090082},{"id":"FzvA.nix","timestamp":1706809112892},{"id":"T4ud.nix","timestamp":1706809133670},{"id":"gJPI.nix","source":"undoRedo.source","timestamp":1706809137930},{"id":"hWLv.nix","timestamp":1706809727079},{"id":"EmqH.nix","timestamp":1706809746147},{"id":"LJiY.nix","timestamp":1706809775236},{"id":"qH85.nix","timestamp":1706809838168},{"id":"Te3f.nix","timestamp":1706809923781},{"id":"vDjX.nix","timestamp":1706809980110},{"id":"Sruz.nix","timestamp":1706810540293},{"id":"3Uc8.nix","source":"moved.source","timestamp":1706810940722}]}